{"name":"ADAS","type":"png24","gridSize":10,"maxWidth":3000,"maxHeight":1000,"imageList":[{"src":"ic_email.png","width":20,"height":12,"top":130,"left":240},{"src":"ic_more_plus.png","width":14,"height":13,"top":20,"left":0},{"src":"ic_phone.png","width":19,"height":18,"top":160,"left":240},{"src":"line_vertical.png","width":1,"height":14,"top":50,"left":0},{"src":"ic_gobtn.png","width":31,"height":31,"top":0,"left":50},{"src":"ic_flag_korea.png","width":24,"height":19,"top":0,"left":90},{"src":"ic_flag_usa.png","width":24,"height":19,"top":0,"left":120},{"src":"ic_home.png","width":19,"height":17,"top":0,"left":150},{"src":"ic_pageback.png","width":30,"height":30,"top":0,"left":170},{"src":"ic_pageback_all.png","width":30,"height":30,"top":0,"left":210},{"src":"ic_pagenext.png","width":30,"height":30,"top":20,"left":90},{"src":"ic_pagenext_all.png","width":30,"height":30,"top":20,"left":130},{"src":"ic_time_01.png","width":41,"height":18,"top":40,"left":10},{"src":"ic_time_02.png","width":41,"height":18,"top":40,"left":170},{"src":"ic_time_03.png","width":41,"height":18,"top":40,"left":220},{"src":"arr_down.png","width":27,"height":19,"top":110,"left":150},{"src":"logo.png","width":106,"height":46,"top":60,"left":10},{"src":"line_orange.png","width":43,"height":2,"top":0,"left":0},{"src":"ic_play.png","width":33,"height":33,"top":60,"left":120},{"src":"ic_rewind.png","width":33,"height":33,"top":60,"left":160},{"src":"ic_forward.png","width":33,"height":33,"top":60,"left":200},{"src":"btn_book.png","width":31,"height":31,"top":100,"left":180},{"src":"ic_play_640.png","width":22,"height":22,"top":10,"left":20},{"src":"ic_rewind_640.png","width":22,"height":22,"top":60,"left":240},{"src":"ic_forward_640.png","width":22,"height":22,"top":90,"left":240},{"src":"arr_dep2.png","width":7,"height":10,"top":0,"left":250},{"src":"btn_dep1_close.png","width":8,"height":1,"top":0,"left":260},{"src":"btn_dep1_open.png","width":8,"height":7,"top":20,"left":250},{"src":"logo_640.png","width":95,"height":41,"top":110,"left":10},{"src":"ic_gobtn_640.png","width":20,"height":20,"top":130,"left":120},{"src":"ic_topbar.png","width":44,"height":2,"top":100,"left":120},{"src":"logo_320.png","width":68,"height":29,"top":160,"left":10},{"src":"middle_dot_640.png","width":3,"height":3,"top":190,"left":250},{"src":"ic_email_320.png","width":12,"height":8,"top":210,"left":240},{"src":"ic_phone_320.png","width":12,"height":11,"top":230,"left":240}]}